ai_dialog_model/__init__.py
ai_dialog_model/config_vars.py
ai_dialog_model/corpus/__init__.py
ai_dialog_model/corpus/corpus.py
ai_dialog_model/corpus/parse_cornell_corpus.py
ai_dialog_model/models/__init__.py
ai_dialog_model/models/seq2seq/__init__.py
ai_dialog_model/models/seq2seq/attn.py
ai_dialog_model/models/seq2seq/encoder.py
ai_dialog_model/models/seq2seq/luong_attn_decoder.py
ai_dialog_model/models/seq2seq/seq2seq_model.py
ai_dialog_model/models/seq2seq/train.py
ai_dialog_model/models/seq2seq/evaluation/__init__.py
ai_dialog_model/models/seq2seq/evaluation/evaluate.py
ai_dialog_model/models/seq2seq/evaluation/greedy_search_decoder.py
ai_dialog_model/models/seq2seq/loss/__init__.py
ai_dialog_model/models/seq2seq/loss/mask_nll_loss.py
ai_dialog_model-0.3.1.dist-info/AUTHORS.rst
ai_dialog_model-0.3.1.dist-info/LICENSE
ai_dialog_model-0.3.1.dist-info/METADATA
ai_dialog_model-0.3.1.dist-info/WHEEL
ai_dialog_model-0.3.1.dist-info/entry_points.txt
ai_dialog_model-0.3.1.dist-info/top_level.txt
ai_dialog_model-0.3.1.dist-info/RECORD
