Metadata-Version: 2.1
Name: ai-dialog-model
Version: 0.3.1
Summary: set of NLG experimentation using deep pavlov library
Home-page: https://github.com/simonmeoni/ai_dialog_model
Author: Simon Meoni
Author-email: 2426884M@student.gla.ac.uk
License: Apache Software License 2.0
Keywords: ai_dialog_model
Platform: UNKNOWN
Classifier: Development Status :: 2 - Pre-Alpha
Classifier: Intended Audience :: Developers
Classifier: License :: OSI Approved :: Apache Software License
Classifier: Natural Language :: English
Classifier: Programming Language :: Python :: 2
Classifier: Programming Language :: Python :: 2.7
Classifier: Programming Language :: Python :: 3
Classifier: Programming Language :: Python :: 3.4
Classifier: Programming Language :: Python :: 3.5
Classifier: Programming Language :: Python :: 3.6
Classifier: Programming Language :: Python :: 3.7
Requires-Dist: Click (>=6.0)
